{
    "$schema": "https://raw.githubusercontent.com/streetsidesoftware/cspell/main/cspell.schema.json",
    "version": "0.2",
    "language": "en",
    "ignorePaths": [
        ".git",
        ".venv",
        ".mypy_cache",
        ".ruff_cache",
        ".pytest_cache",
        "build",
        "dist",
        "*.lock",
        "uv.lock"
    ],
    "words": [
        "cov",
        "docstrings",
        "frozenset",
        "functools",
        "getattr",
        "hatchling",
        "izuno",
        "loaders",
        "mypy",
        "paramspec",
        "pyproject",
        "pytest",
        "Pythonic",
        "rbac",
        "ruff",
        "snakecase",
        "streamlit",
        "taplo",
        "typevar",
        "wraps"
    ],
    "enableFiletypes": [
        "python",
        "markdown",
        "toml",
        "yaml"
    ]
}
